arramooz/__init__.py
arramooz/arabicdictionary.py
arramooz/nountuple.py
arramooz/stopwordsdictionaryclass.py
arramooz/verbtuple.py
arramooz/wordfreqdictionaryclass.py
arramooz/data/.~lock.prop_noun.csv#
arramooz/data/arabicdictionary (نسخة).sqlite
arramooz/data/arabicdictionary.sqlite
arramooz/data/nouns_sqliteStructure.sql
arramooz/data/randomtext.txt
arramooz/data/stopwords.sqlite
arramooz/data/stopwords2.sqlite
arramooz/data/stopwords3.sqlite
arramooz/data/verbs.dict.sqliteStructure.sql
arramooz/data/wordfreq.sqlite
arramooz/data/wordfreq.sqliteStructure.sql
arramooz_pysqlite-0.4.1.dist-info/AUTHORS.md
arramooz_pysqlite-0.4.1.dist-info/LICENSE
arramooz_pysqlite-0.4.1.dist-info/METADATA
arramooz_pysqlite-0.4.1.dist-info/WHEEL
arramooz_pysqlite-0.4.1.dist-info/top_level.txt
arramooz_pysqlite-0.4.1.dist-info/RECORD
